winicode/__init__.py
winicode-0.0.5.dist-info/DESCRIPTION.rst
winicode-0.0.5.dist-info/METADATA
winicode-0.0.5.dist-info/RECORD
winicode-0.0.5.dist-info/WHEEL
winicode-0.0.5.dist-info/metadata.json
winicode-0.0.5.dist-info/top_level.txt
